isomorphic
smartClient
