Metadata-Version: 1.1
Name: pysmartclient
Version: 0.9.4
Summary: A smartClient wrapper
Home-page: https://github.com/peppicus/pysmartclient.git
Author: peppicus
Author-email: homepeppicus@gmail.com
License: MIT
Keywords: web gui interface ajax web2.0
Platform: UNKNOWN
Classifier: Development Status :: 4 - Beta
Classifier: Intended Audience :: Developers
Classifier: Topic :: Software Development :: Build Tools
Classifier: License :: OSI Approved :: MIT License
Classifier: Programming Language :: Python :: 2
Classifier: Programming Language :: Python :: 2.6
Classifier: Programming Language :: Python :: 2.7
Classifier: Programming Language :: Python :: 3
Classifier: Programming Language :: Python :: 3.3
Classifier: Programming Language :: Python :: 3.4
Classifier: Programming Language :: Python :: 3.5
